ln_io_h5_csv/__init__.py
ln_io_h5_csv/abstract_in_h5_csv.py
ln_io_h5_csv/annotate_channel.py
ln_io_h5_csv/in_h5_csv.py
ln_io_h5_csv/in_playback_h5_csv.py
ln_io_h5_csv/out_h5_csv.py
LN_IO_h5_csv-1.0.0.dist-info/AUTHORS.rst
LN_IO_h5_csv-1.0.0.dist-info/LICENSE
LN_IO_h5_csv-1.0.0.dist-info/METADATA
LN_IO_h5_csv-1.0.0.dist-info/WHEEL
LN_IO_h5_csv-1.0.0.dist-info/entry_points.txt
LN_IO_h5_csv-1.0.0.dist-info/top_level.txt
LN_IO_h5_csv-1.0.0.dist-info/zip-safe
LN_IO_h5_csv-1.0.0.dist-info/RECORD
