Metadata-Version: 2.1
Name: LN-IO-h5-csv
Version: 1.0.0
Summary: LiveNodes: node based live streaming sensor/data and visualization suite.
Author-email: Yale Hartmann <yale.hartmann@uni-bremen.de>
License: GNU GENERAL PUBLIC LICENSE
License-File: LICENSE
License-File: AUTHORS.rst
Requires-Dist: livenodes>=v0.12.1b1
Requires-Dist: ln-ports>=0.12.1b1
Requires-Dist: ln-io-python>=0.12.1b1
Requires-Dist: numpy>=1.24.4
Requires-Dist: h5py
Requires-Dist: joblib>=1.4.2
Requires-Dist: pyarrow>=16.0.0
Provides-Extra: dev
Requires-Dist: tox; extra == "dev"
Requires-Dist: pytest>=8.2.2; extra == "dev"
